{
  "bill_id": 1925484,
  "change_hash": "0dbf557c1774a568e41cb7235e131f02",
  "session_id": 2137,
  "session": {
    "session_id": 2137,
    "state_id": 44,
    "year_start": 2025,
    "year_end": 2025,
    "prefile": 0,
    "sine_die": 0,
    "prior": 0,
    "special": 0,
    "session_tag": "Regular Session",
    "session_title": "2025 Regular Session",
    "session_name": "2025 General Session"
  },
  "url": "https://legiscan.com/UT/bill/HB0249/2025",
  "state_link": "https://le.utah.gov/~2025/bills/static/HB0249.html",
  "completed": 0,
  "status": 2,
  "status_date": "2025-02-05",
  "progress": [
    {
      "date": "2025-01-21",
      "event": 1
    },
    {
      "date": "2025-01-24",
      "event": 9
    },
    {
      "date": "2025-01-28",
      "event": 10
    },
    {
      "date": "2025-02-05",
      "event": 2
    },
    {
      "date": "2025-02-10",
      "event": 9
    },
    {
      "date": "2025-02-14",
      "event": 10
    }
  ],
  "state": "UT",
  "state_id": 44,
  "bill_number": "HB0249",
  "bill_type": "B",
  "bill_type_id": "1",
  "body": "H",
  "body_id": 93,
  "current_body": "S",
  "current_body_id": 94,
  "title": "Nuclear Power Amendments",
  "description": "Nuclear Power Amendments",
  "pending_committee_id": 0,
  "committee": [],
  "referrals": [
    {
      "date": "2025-01-21",
      "committee_id": 2116,
      "chamber": "H",
      "chamber_id": 93,
      "name": "Rules"
    },
    {
      "date": "2025-01-24",
      "committee_id": 5049,
      "chamber": "H",
      "chamber_id": 93,
      "name": "Public Utilities and Energy"
    },
    {
      "date": "2025-02-06",
      "committee_id": 2128,
      "chamber": "S",
      "chamber_id": 94,
      "name": "Rules"
    },
    {
      "date": "2025-02-10",
      "committee_id": 3583,
      "chamber": "S",
      "chamber_id": 94,
      "name": "Transportation, Public Utilities, Energy, and Technology"
    }
  ],
  "history": [
    {
      "date": "2025-01-16",
      "action": "Bill Numbered but not Distributed in Legislative Research and General Counsel",
      "chamber": "",
      "chamber_id": 0,
      "importance": 0
    },
    {
      "date": "2025-01-16",
      "action": "Numbered Bill Publicly Distributed in Legislative Research and General Counsel",
      "chamber": "",
      "chamber_id": 0,
      "importance": 0
    },
    {
      "date": "2025-01-21",
      "action": "House/ received bill from Legislative Research in Clerk of the House",
      "chamber": "H",
      "chamber_id": 93,
      "importance": 0
    },
    {
      "date": "2025-01-21",
      "action": "House/ 1st reading (Introduced) in House Rules Committee",
      "chamber": "H",
      "chamber_id": 93,
      "importance": 1
    },
    {
      "date": "2025-01-23",
      "action": "House/ received fiscal note from Fiscal Analyst in House Rules Committee",
      "chamber": "H",
      "chamber_id": 93,
      "importance": 0
    },
    {
      "date": "2025-01-24",
      "action": "House/ to standing committee in House Public Utilities and Energy Committee",
      "chamber": "H",
      "chamber_id": 93,
      "importance": 1
    },
    {
      "date": "2025-01-27",
      "action": "House Comm - Substitute Recommendation in House Public Utilities and Energy Committee",
      "chamber": "H",
      "chamber_id": 93,
      "importance": 0
    },
    {
      "date": "2025-01-27",
      "action": "House Comm - Favorable Recommendation in House Public Utilities and Energy Committee",
      "chamber": "H",
      "chamber_id": 93,
      "importance": 0
    },
    {
      "date": "2025-01-28",
      "action": "House/ comm rpt/ substituted in House Public Utilities and Energy Committee",
      "chamber": "H",
      "chamber_id": 93,
      "importance": 1
    },
    {
      "date": "2025-01-28",
      "action": "House/ 2nd reading in House 3rd Reading Calendar for House bills",
      "chamber": "H",
      "chamber_id": 93,
      "importance": 0
    },
    {
      "date": "2025-02-05",
      "action": "House/ 3rd reading in House 3rd Reading Calendar for House bills",
      "chamber": "H",
      "chamber_id": 93,
      "importance": 0
    },
    {
      "date": "2025-02-05",
      "action": "House/ passed 3rd reading in Senate Secretary",
      "chamber": "S",
      "chamber_id": 94,
      "importance": 0
    },
    {
      "date": "2025-02-05",
      "action": "House/ to Senate in Senate Secretary",
      "chamber": "S",
      "chamber_id": 94,
      "importance": 0
    },
    {
      "date": "2025-02-05",
      "action": "Senate/ received from House in Waiting for Introduction in the Senate",
      "chamber": "S",
      "chamber_id": 94,
      "importance": 1
    },
    {
      "date": "2025-02-06",
      "action": "Senate/ 1st reading (Introduced) in Senate Rules Committee",
      "chamber": "S",
      "chamber_id": 94,
      "importance": 0
    },
    {
      "date": "2025-02-10",
      "action": "Senate/ to standing committee in Senate Transportation, Public Utilities, Energy, and Technology Committee",
      "chamber": "S",
      "chamber_id": 94,
      "importance": 1
    },
    {
      "date": "2025-02-13",
      "action": "Senate Comm - Substitute Recommendation in Senate Transportation, Public Utilities, Energy, and Technology Committee",
      "chamber": "S",
      "chamber_id": 94,
      "importance": 0
    },
    {
      "date": "2025-02-13",
      "action": "Senate Comm - Amendment Recommendation in Senate Transportation, Public Utilities, Energy, and Technology Committee",
      "chamber": "S",
      "chamber_id": 94,
      "importance": 0
    },
    {
      "date": "2025-02-13",
      "action": "Senate Comm - Favorable Recommendation in Senate Transportation, Public Utilities, Energy, and Technology Committee",
      "chamber": "S",
      "chamber_id": 94,
      "importance": 0
    },
    {
      "date": "2025-02-14",
      "action": "Senate/ comm rpt/ substituted/ amended in Senate Transportation, Public Utilities, Energy, and Technology Committee",
      "chamber": "S",
      "chamber_id": 94,
      "importance": 1
    },
    {
      "date": "2025-02-14",
      "action": "Senate/ placed on 2nd Reading Calendar in Senate 2nd Reading Calendar",
      "chamber": "S",
      "chamber_id": 94,
      "importance": 0
    },
    {
      "date": "2025-02-19",
      "action": "Senate/ 2nd reading in Senate 2nd Reading Calendar",
      "chamber": "S",
      "chamber_id": 94,
      "importance": 0
    },
    {
      "date": "2025-02-19",
      "action": "Senate/ circled in Senate 2nd Reading Calendar",
      "chamber": "S",
      "chamber_id": 94,
      "importance": 0
    }
  ],
  "sponsors": [
    {
      "people_id": 18110,
      "person_hash": "d6dp8cmr",
      "party_id": "2",
      "state_id": 44,
      "party": "R",
      "role_id": 1,
      "role": "Rep",
      "name": "Carl Albrecht",
      "first_name": "Carl",
      "middle_name": "R.",
      "last_name": "Albrecht",
      "suffix": "",
      "nickname": "",
      "district": "HD-070",
      "ftm_eid": 27891625,
      "votesmart_id": 168710,
      "opensecrets_id": "",
      "knowwho_pid": 574027,
      "ballotpedia": "Carl_R._Albrecht",
      "bioguide_id": "",
      "sponsor_type_id": 1,
      "sponsor_order": 1,
      "committee_sponsor": 0,
      "committee_id": 0,
      "state_federal": 0
    },
    {
      "people_id": 17396,
      "person_hash": "h60i2z3a",
      "party_id": "2",
      "state_id": 44,
      "party": "R",
      "role_id": 2,
      "role": "Sen",
      "name": "Ann Millner",
      "first_name": "Ann",
      "middle_name": "",
      "last_name": "Millner",
      "suffix": "",
      "nickname": "",
      "district": "SD-005",
      "ftm_eid": 24352067,
      "votesmart_id": 151613,
      "opensecrets_id": "",
      "knowwho_pid": 492263,
      "ballotpedia": "Ann_Millner",
      "bioguide_id": "",
      "sponsor_type_id": 3,
      "sponsor_order": 2,
      "committee_sponsor": 0,
      "committee_id": 0,
      "state_federal": 0
    }
  ],
  "sasts": [],
  "subjects": [
    {
      "subject_id": 360912,
      "subject_name": "Public Utilities and Technology"
    },
    {
      "subject_id": 11909,
      "subject_name": "Counties"
    },
    {
      "subject_id": 11966,
      "subject_name": "Public Funds and Accounts"
    },
    {
      "subject_id": 11930,
      "subject_name": "Energy"
    },
    {
      "subject_id": 11949,
      "subject_name": "Public Utilities"
    },
    {
      "subject_id": 332649,
      "subject_name": "Municipalities"
    },
    {
      "subject_id": 11924,
      "subject_name": "Property Tax"
    },
    {
      "subject_id": 332739,
      "subject_name": "Utilities Siting and Permitting"
    },
    {
      "subject_id": 11888,
      "subject_name": "Revenue and Taxation"
    },
    {
      "subject_id": 374640,
      "subject_name": "Office of Energy Development"
    }
  ],
  "texts": [
    {
      "doc_id": 3062758,
      "date": "2025-01-16",
      "type": "Introduced",
      "type_id": 1,
      "mime": "application/pdf",
      "mime_id": 2,
      "url": "https://legiscan.com/UT/text/HB0249/id/3062758",
      "state_link": "https://le.utah.gov/Session/2025/bills/introduced/HB0249.pdf",
      "text_size": 59797,
      "text_hash": "5dc0283ec0c7ba77571c70fa733a0113",
      "alt_bill_text": 0,
      "alt_mime": "",
      "alt_mime_id": 0,
      "alt_state_link": "",
      "alt_text_size": 0,
      "alt_text_hash": ""
    },
    {
      "doc_id": 3087632,
      "date": "2025-01-25",
      "type": "Substitute",
      "type_id": 14,
      "mime": "application/pdf",
      "mime_id": 2,
      "url": "https://legiscan.com/UT/text/HB0249/id/3087632",
      "state_link": "https://le.utah.gov/Session/2025/bills/introduced/HB0249S01.pdf",
      "text_size": 85738,
      "text_hash": "fc7dce450524413651d26cfab7f89707",
      "alt_bill_text": 0,
      "alt_mime": "",
      "alt_mime_id": 0,
      "alt_state_link": "",
      "alt_text_size": 0,
      "alt_text_hash": ""
    },
    {
      "doc_id": 3109881,
      "date": "2025-02-07",
      "type": "Substitute",
      "type_id": 14,
      "mime": "application/pdf",
      "mime_id": 2,
      "url": "https://legiscan.com/UT/text/HB0249/id/3109881",
      "state_link": "https://le.utah.gov/Session/2025/bills/introduced/HB0249S02.pdf",
      "text_size": 86284,
      "text_hash": "f13fd83a99c532f61c874baf666622a2",
      "alt_bill_text": 0,
      "alt_mime": "",
      "alt_mime_id": 0,
      "alt_state_link": "",
      "alt_text_size": 0,
      "alt_text_hash": ""
    },
    {
      "doc_id": 3121944,
      "date": "2025-02-14",
      "type": "Amended",
      "type_id": 3,
      "mime": "application/pdf",
      "mime_id": 2,
      "url": "https://legiscan.com/UT/text/HB0249/id/3121944",
      "state_link": "https://le.utah.gov/Session/2025/bills/amended/AV_HB0249S02_2025-02-14_09-02-27.pdf",
      "text_size": 99818,
      "text_hash": "616bc3807b59dc5c20d44328902a623f",
      "alt_bill_text": 0,
      "alt_mime": "",
      "alt_mime_id": 0,
      "alt_state_link": "",
      "alt_text_size": 0,
      "alt_text_hash": ""
    }
  ],
  "votes": [],
  "amendments": [
    {
      "amendment_id": 227297,
      "adopted": 1,
      "chamber": "H",
      "chamber_id": 93,
      "date": "2025-02-12",
      "title": "House Amendment 1",
      "description": "House Amendment 1",
      "mime": "application/pdf",
      "mime_id": 2,
      "url": "https://legiscan.com/UT/amendment/HB0249/id/227297",
      "state_link": "https://le.utah.gov/Session/2025/bills/amended/HB0249S02.Hamd.1.pdf",
      "amendment_size": 9879,
      "amendment_hash": "29f4d04f9c861f4665d9bf314ec5ff63",
      "alt_amendment": 0,
      "alt_mime": "",
      "alt_mime_id": 0,
      "alt_state_link": "",
      "alt_amendment_size": 0,
      "alt_amendment_hash": ""
    }
  ],
  "supplements": [
    {
      "supplement_id": 497676,
      "date": "2025-01-25",
      "type": "Misc",
      "type_id": 7,
      "title": "Misc",
      "description": "Comparison to Sub #0",
      "mime": "application/pdf",
      "mime_id": 2,
      "url": "https://legiscan.com/UT/supplement/HB0249/id/497676",
      "state_link": "https://le.utah.gov/Session/2025/bills/introduced/CP%20HB0249%20To%20HB0249S01.pdf",
      "supplement_size": 99042,
      "supplement_hash": "230c92bf164ab0a7947247316faed18d",
      "alt_supplement": 0,
      "alt_mime": "",
      "alt_mime_id": 0,
      "alt_state_link": "",
      "alt_supplement_size": 0,
      "alt_supplement_hash": ""
    },
    {
      "supplement_id": 497677,
      "date": "2025-01-27",
      "type": "Misc",
      "type_id": 7,
      "title": "Misc",
      "description": "House Committee Report HB0249",
      "mime": "application/pdf",
      "mime_id": 2,
      "url": "https://legiscan.com/UT/supplement/HB0249/id/497677",
      "state_link": "https://le.utah.gov/Session/2025/comreport/HB249H10.pdf",
      "supplement_size": 143132,
      "supplement_hash": "fdfe1ad908812ce09d192de361469465",
      "alt_supplement": 0,
      "alt_mime": "",
      "alt_mime_id": 0,
      "alt_state_link": "",
      "alt_supplement_size": 0,
      "alt_supplement_hash": ""
    },
    {
      "supplement_id": 498909,
      "date": "2025-01-22",
      "type": "Fiscal Note",
      "type_id": 1,
      "title": "Fiscal Note",
      "description": "Fiscal Note HB0249",
      "mime": "application/pdf",
      "mime_id": 2,
      "url": "https://legiscan.com/UT/supplement/HB0249/id/498909",
      "state_link": "https://pf.utleg.gov/public-web/sessions/2025GS/fiscal-notes/HB0249.fn.pdf",
      "supplement_size": 1610178,
      "supplement_hash": "af7799b227f621d18a70ca911f3c7fd9",
      "alt_supplement": 0,
      "alt_mime": "",
      "alt_mime_id": 0,
      "alt_state_link": "",
      "alt_supplement_size": 0,
      "alt_supplement_hash": ""
    },
    {
      "supplement_id": 503725,
      "date": "2025-01-29",
      "type": "Fiscal Note",
      "type_id": 1,
      "title": "Fiscal Note",
      "description": "Fiscal Note HB0249S01",
      "mime": "application/pdf",
      "mime_id": 2,
      "url": "https://legiscan.com/UT/supplement/HB0249/id/503725",
      "state_link": "https://pf.utleg.gov/public-web/sessions/2025GS/fiscal-notes/HB0249S01.fn.pdf",
      "supplement_size": 1610261,
      "supplement_hash": "519b8dfa70a4a9e41f2c5a3102de9ff0",
      "alt_supplement": 0,
      "alt_mime": "",
      "alt_mime_id": 0,
      "alt_state_link": "",
      "alt_supplement_size": 0,
      "alt_supplement_hash": ""
    },
    {
      "supplement_id": 509126,
      "date": "2025-02-07",
      "type": "Misc",
      "type_id": 7,
      "title": "Misc",
      "description": "Comparison to Sub #0",
      "mime": "application/pdf",
      "mime_id": 2,
      "url": "https://legiscan.com/UT/supplement/HB0249/id/509126",
      "state_link": "https://le.utah.gov/Session/2025/bills/introduced/CP%20HB0249%20To%20HB0249S02.pdf",
      "supplement_size": 101098,
      "supplement_hash": "b88b4d335ad2766d875f4d6ae0840714",
      "alt_supplement": 0,
      "alt_mime": "",
      "alt_mime_id": 0,
      "alt_state_link": "",
      "alt_supplement_size": 0,
      "alt_supplement_hash": ""
    },
    {
      "supplement_id": 509127,
      "date": "2025-02-07",
      "type": "Misc",
      "type_id": 7,
      "title": "Misc",
      "description": "Comparison to Sub #1",
      "mime": "application/pdf",
      "mime_id": 2,
      "url": "https://legiscan.com/UT/supplement/HB0249/id/509127",
      "state_link": "https://le.utah.gov/Session/2025/bills/introduced/CP%20HB0249S01%20To%20HB0249S02.pdf",
      "supplement_size": 83295,
      "supplement_hash": "5b0921c886ecedefeab38fb3f3ffc1a2",
      "alt_supplement": 0,
      "alt_mime": "",
      "alt_mime_id": 0,
      "alt_state_link": "",
      "alt_supplement_size": 0,
      "alt_supplement_hash": ""
    },
    {
      "supplement_id": 511996,
      "date": "2025-02-11",
      "type": "Fiscal Note",
      "type_id": 1,
      "title": "Fiscal Note",
      "description": "Fiscal Note HB0249S02",
      "mime": "application/pdf",
      "mime_id": 2,
      "url": "https://legiscan.com/UT/supplement/HB0249/id/511996",
      "state_link": "https://pf.utleg.gov/public-web/sessions/2025GS/fiscal-notes/HB0249S02.fn.pdf",
      "supplement_size": 1610262,
      "supplement_hash": "248ca72f60fd0965b38ae50178040aa9",
      "alt_supplement": 0,
      "alt_mime": "",
      "alt_mime_id": 0,
      "alt_state_link": "",
      "alt_supplement_size": 0,
      "alt_supplement_hash": ""
    },
    {
      "supplement_id": 516049,
      "date": "2025-02-13",
      "type": "Misc",
      "type_id": 7,
      "title": "Misc",
      "description": "Senate Committee Report HB0249",
      "mime": "application/pdf",
      "mime_id": 2,
      "url": "https://legiscan.com/UT/supplement/HB0249/id/516049",
      "state_link": "https://le.utah.gov/Session/2025/comreport/HB249S10.pdf",
      "supplement_size": 157026,
      "supplement_hash": "055a8eaf343bc9740a5a6d51042cef82",
      "alt_supplement": 0,
      "alt_mime": "",
      "alt_mime_id": 0,
      "alt_state_link": "",
      "alt_supplement_size": 0,
      "alt_supplement_hash": ""
    }
  ],
  "calendar": [
    {
      "type_id": 1,
      "event_hash": "8a482876",
      "type": "Hearing",
      "date": "2025-01-27",
      "time": "15:00",
      "location": "",
      "description": "House Public Utilities and Energy Hearing"
    },
    {
      "type_id": 1,
      "event_hash": "04a871aa",
      "type": "Hearing",
      "date": "2025-02-13",
      "time": "14:00",
      "location": "Room 30 House Building",
      "description": "Senate Transportation, Public Utilities, Energy, and Technology Hearing"
    }
  ],
  "general_provisions": "This bill creates the Nuclear Energy Consortium and the Utah Energy Council, establishes a process for designating energy development zones, and creates the Energy Development Investment Fund.",
  "hilighted_provisions": "This bill:<hr><ltbullet>defines terms;<hr><ltbullet>creates the Nuclear Energy Consortium within the Office of Energy Development (office) and establishes its membership and duties;<hr><ltbullet>creates the Utah Energy Council within the office and establishes its membership and duties;<hr><ltbullet>modifies the duties and name of the Utah San Rafael Energy Lab Board;<hr><ltbullet>establishes a process for designating electrical energy development zones;<hr><ltbullet>creates the Electrical Energy Development Investment Fund and provides for its administration; and<hr><ltbullet>establishes authorized uses of fund money.",
  "monies": "None",
  "attorney": "Scott Elder",
  "fiscal_analyst": "Lacey K. Moore",
  "gov_tracking_id": "IOVEXLABVU",
  "comrecommend": [],
  "agendas": [
    {
      "mtgID": "19660",
      "committeeID": "HSTPUT",
      "mtgDate": "2025-01-27 15:00:00.0",
      "agendaItem": "1",
      "mtgPlace": "110 Senate Building",
      "committeeName": "House Public Utilities and Energy Committee",
      "upcomming": false,
      "minutesURL": "/interim/2025/html/00000724.htm",
      "agendaURL": "/~2025/agenda/HPUT0127.ag.htm",
      "billSession": "2025GS",
      "markerID": "264559"
    },
    {
      "mtgID": "19801",
      "committeeID": "SSTTPT",
      "mtgDate": "2025-02-13 14:00:00.0",
      "agendaItem": "3",
      "mtgPlace": "220 Senate Building",
      "committeeName": "Senate Transportation, Public Utilities, Energy, and Technology Committee",
      "upcomming": false,
      "minutesURL": "/interim/2025/html/00001603.htm",
      "agendaURL": "/~2025/agenda/STPT0213.ag.htm",
      "billSession": "2025GS",
      "markerID": "271301"
    }
  ],
  "last_action": "Senate/ circled",
  "last_action_owner": "Senate 2nd Reading Calendar",
  "last_action_time": "2/19/2025",
  "action_history": [
    {
      "description": "Bill Numbered but not Distributed",
      "owner": "Legislative Research and General Counsel",
      "actionDate": "1/16/2025 2:50 PM",
      "actionClass": "L",
      "voteID": "",
      "voiceVote": "",
      "voteHouse": "",
      "voteStr": "",
      "actionCode": "LNUMBER",
      "parm2": "",
      "parm1": ""
    },
    {
      "description": "Numbered Bill Publicly Distributed",
      "owner": "Legislative Research and General Counsel",
      "actionDate": "1/16/2025 2:50 PM",
      "actionClass": "L",
      "voteID": "",
      "voiceVote": "",
      "voteHouse": "",
      "voteStr": "",
      "actionCode": "LLFA",
      "parm2": "",
      "parm1": ""
    },
    {
      "description": "House/ received bill from Legislative Research",
      "owner": "Clerk of the House",
      "actionDate": "1/21/2025 8:50 AM",
      "actionClass": "H",
      "voteID": "",
      "voiceVote": "",
      "voteHouse": "",
      "voteStr": "",
      "actionCode": "HRECLRGC",
      "parm2": "",
      "parm1": ""
    },
    {
      "description": "House/ 1st reading (Introduced)",
      "owner": "House Rules Committee",
      "actionDate": "1/21/2025 3:28 PM",
      "actionClass": "H",
      "voteID": "",
      "voiceVote": "",
      "voteHouse": "",
      "voteStr": "",
      "actionCode": "HREAD1",
      "parm2": "",
      "parm1": ""
    },
    {
      "description": "House/ received fiscal note from Fiscal Analyst",
      "owner": "House Rules Committee",
      "actionDate": "1/23/2025 10:16 AM",
      "actionClass": "H",
      "voteID": "",
      "voiceVote": "",
      "voteHouse": "",
      "voteStr": "",
      "actionCode": "HRECLFA",
      "parm2": "",
      "parm1": ""
    },
    {
      "description": "House/ to standing committee",
      "owner": "House Public Utilities and Energy Committee",
      "actionDate": "1/24/2025 12:05 PM",
      "actionClass": "H",
      "voteID": "",
      "voiceVote": "",
      "voteHouse": "",
      "voteStr": "",
      "actionCode": "HTOSTAND",
      "parm2": "",
      "parm1": ""
    },
    {
      "description": "House Comm - Substitute Recommendation",
      "owner": "House Public Utilities and Energy Committee",
      "actionDate": "1/27/2025 4:16 PM",
      "actionClass": "A",
      "voteID": "34329",
      "voiceVote": "",
      "voteHouse": "",
      "voteStr": "10-0-3",
      "actionCode": "HCASUB",
      "parm2": "0",
      "parm1": "1"
    },
    {
      "description": "House Comm - Favorable Recommendation",
      "owner": "House Public Utilities and Energy Committee",
      "actionDate": "1/27/2025 4:19 PM",
      "actionClass": "A",
      "voteID": "34330",
      "voiceVote": "",
      "voteHouse": "",
      "voteStr": "10-0-3",
      "actionCode": "HCAFAV",
      "parm2": "",
      "parm1": ""
    },
    {
      "description": "House/ comm rpt/ substituted",
      "owner": "House Public Utilities and Energy Committee",
      "actionDate": "1/28/2025 11:13 AM",
      "actionClass": "H",
      "voteID": "",
      "voiceVote": "",
      "voteHouse": "",
      "voteStr": "",
      "actionCode": "HCRSUB",
      "parm2": "",
      "parm1": ""
    },
    {
      "description": "House/ 2nd reading",
      "owner": "House 3rd Reading Calendar for House bills",
      "actionDate": "1/28/2025 11:13 AM",
      "actionClass": "H",
      "voteID": "",
      "voiceVote": "",
      "voteHouse": "",
      "voteStr": "",
      "actionCode": "HREAD2",
      "parm2": "",
      "parm1": ""
    },
    {
      "description": "House/ 3rd reading",
      "owner": "House 3rd Reading Calendar for House bills",
      "actionDate": "2/5/2025 2:24 PM",
      "actionClass": "H",
      "voteID": "",
      "voiceVote": "",
      "voteHouse": "",
      "voteStr": "",
      "actionCode": "HREAD3",
      "parm2": "",
      "parm1": ""
    },
    {
      "description": "House/ passed 3rd reading",
      "owner": "Senate Secretary",
      "actionDate": "2/5/2025 2:33 PM",
      "actionClass": "H",
      "voteID": "182",
      "voiceVote": "0",
      "voteHouse": "H",
      "voteStr": "72-0-3",
      "actionCode": "HPASS3",
      "parm2": "",
      "parm1": ""
    },
    {
      "description": "House/ to Senate",
      "owner": "Senate Secretary",
      "actionDate": "2/5/2025 2:33 PM",
      "actionClass": "H",
      "voteID": "",
      "voiceVote": "",
      "voteHouse": "",
      "voteStr": "",
      "actionCode": "HTOSEN",
      "parm2": "",
      "parm1": ""
    },
    {
      "description": "Senate/ received from House",
      "owner": "Waiting for Introduction in the Senate",
      "actionDate": "2/5/2025 5:37 PM",
      "actionClass": "S",
      "voteID": "",
      "voiceVote": "",
      "voteHouse": "",
      "voteStr": "",
      "actionCode": "SRECH",
      "parm2": "",
      "parm1": ""
    },
    {
      "description": "Senate/ 1st reading (Introduced)",
      "owner": "Senate Rules Committee",
      "actionDate": "2/6/2025 11:09 AM",
      "actionClass": "S",
      "voteID": "",
      "voiceVote": "",
      "voteHouse": "",
      "voteStr": "",
      "actionCode": "SREAD1",
      "parm2": "",
      "parm1": ""
    },
    {
      "description": "Senate/ to standing committee",
      "owner": "Senate Transportation, Public Utilities, Energy, and Technology Committee",
      "actionDate": "2/10/2025 2:16 PM",
      "actionClass": "S",
      "voteID": "",
      "voiceVote": "",
      "voteHouse": "",
      "voteStr": "",
      "actionCode": "STOSTAND",
      "parm2": "",
      "parm1": ""
    },
    {
      "description": "Senate Comm - Substitute Recommendation",
      "owner": "Senate Transportation, Public Utilities, Energy, and Technology Committee",
      "actionDate": "2/13/2025 2:19 PM",
      "actionClass": "A",
      "voteID": "35504",
      "voiceVote": "",
      "voteHouse": "",
      "voteStr": "6-0-2",
      "actionCode": "SCASUB",
      "parm2": "1",
      "parm1": "2"
    },
    {
      "description": "Senate Comm - Amendment Recommendation",
      "owner": "Senate Transportation, Public Utilities, Energy, and Technology Committee",
      "actionDate": "2/13/2025 2:19 PM",
      "actionClass": "A",
      "voteID": "35507",
      "voiceVote": "",
      "voteHouse": "",
      "voteStr": "6-0-2",
      "actionCode": "SCAAMD",
      "parm2": "",
      "parm1": "1"
    },
    {
      "description": "Senate Comm - Favorable Recommendation",
      "owner": "Senate Transportation, Public Utilities, Energy, and Technology Committee",
      "actionDate": "2/13/2025 2:45 PM",
      "actionClass": "A",
      "voteID": "35523",
      "voiceVote": "",
      "voteHouse": "",
      "voteStr": "6-0-2",
      "actionCode": "SCAFAV",
      "parm2": "",
      "parm1": ""
    },
    {
      "description": "Senate/ comm rpt/ substituted/ amended",
      "owner": "Senate Transportation, Public Utilities, Energy, and Technology Committee",
      "actionDate": "2/14/2025 10:27 AM",
      "actionClass": "S",
      "voteID": "",
      "voiceVote": "",
      "voteHouse": "",
      "voteStr": "",
      "actionCode": "SCRSUBAMD",
      "parm2": "",
      "parm1": ""
    },
    {
      "description": "Senate/ placed on 2nd Reading Calendar",
      "owner": "Senate 2nd Reading Calendar",
      "actionDate": "2/14/2025 10:27 AM",
      "actionClass": "S",
      "voteID": "",
      "voiceVote": "",
      "voteHouse": "",
      "voteStr": "",
      "actionCode": "SON2ND",
      "parm2": "",
      "parm1": ""
    },
    {
      "description": "Senate/ 2nd reading",
      "owner": "Senate 2nd Reading Calendar",
      "actionDate": "2/19/2025 3:22 PM",
      "actionClass": "S",
      "voteID": "",
      "voiceVote": "",
      "voteHouse": "",
      "voteStr": "",
      "actionCode": "SREAD2",
      "parm2": "",
      "parm1": ""
    },
    {
      "description": "Senate/ circled",
      "owner": "Senate 2nd Reading Calendar",
      "actionDate": "2/19/2025 3:22 PM",
      "actionClass": "S",
      "voteID": "741",
      "voiceVote": "1",
      "voteHouse": "S",
      "voteStr": "0-0-29",
      "actionCode": "SCIRCLED",
      "parm2": "",
      "parm1": ""
    }
  ]
}