{
  "bill_id": 1964227,
  "change_hash": "08b531aaa22ceda8be1ff2564e9a0170",
  "session_id": 2137,
  "session": {
    "session_id": 2137,
    "state_id": 44,
    "year_start": 2025,
    "year_end": 2025,
    "prefile": 0,
    "sine_die": 0,
    "prior": 0,
    "special": 0,
    "session_tag": "Regular Session",
    "session_title": "2025 Regular Session",
    "session_name": "2025 General Session"
  },
  "url": "https://legiscan.com/UT/bill/SB0252/2025",
  "state_link": "https://le.utah.gov/~2025/bills/static/SB0252.html",
  "completed": 0,
  "status": 2,
  "status_date": "2025-02-27",
  "progress": [
    {
      "date": "2025-02-11",
      "event": 1
    },
    {
      "date": "2025-02-11",
      "event": 9
    },
    {
      "date": "2025-02-18",
      "event": 10
    },
    {
      "date": "2025-02-27",
      "event": 2
    },
    {
      "date": "2025-03-03",
      "event": 9
    },
    {
      "date": "2025-03-04",
      "event": 10
    }
  ],
  "state": "UT",
  "state_id": 44,
  "bill_number": "SB0252",
  "bill_type": "B",
  "bill_type_id": "1",
  "body": "S",
  "body_id": 94,
  "current_body": "H",
  "current_body_id": 93,
  "title": "Digital Information Seizure Amendments",
  "description": "Digital Information Seizure Amendments",
  "pending_committee_id": 0,
  "committee": [],
  "referrals": [
    {
      "date": "2025-02-11",
      "committee_id": 2128,
      "chamber": "S",
      "chamber_id": 94,
      "name": "Rules"
    },
    {
      "date": "2025-02-11",
      "committee_id": 2124,
      "chamber": "S",
      "chamber_id": 94,
      "name": "Judiciary, Law Enforcement, and Criminal Justice"
    },
    {
      "date": "2025-02-28",
      "committee_id": 2116,
      "chamber": "H",
      "chamber_id": 93,
      "name": "Rules"
    },
    {
      "date": "2025-03-03",
      "committee_id": 2110,
      "chamber": "H",
      "chamber_id": 93,
      "name": "Law Enforcement and Criminal Justice"
    }
  ],
  "history": [
    {
      "date": "2025-02-10",
      "action": "Bill Numbered but not Distributed in Legislative Research and General Counsel",
      "chamber": "",
      "chamber_id": 0,
      "importance": 0
    },
    {
      "date": "2025-02-10",
      "action": "Numbered Bill Publicly Distributed in Legislative Research and General Counsel",
      "chamber": "",
      "chamber_id": 0,
      "importance": 0
    },
    {
      "date": "2025-02-11",
      "action": "Senate/ received bill from Legislative Research in Waiting for Introduction in the Senate",
      "chamber": "S",
      "chamber_id": 94,
      "importance": 0
    },
    {
      "date": "2025-02-11",
      "action": "Senate/ 1st reading (Introduced) in Senate Rules Committee",
      "chamber": "S",
      "chamber_id": 94,
      "importance": 1
    },
    {
      "date": "2025-02-11",
      "action": "Senate/ to standing committee in Senate Judiciary, Law Enforcement, and Criminal Justice Committee",
      "chamber": "S",
      "chamber_id": 94,
      "importance": 1
    },
    {
      "date": "2025-02-12",
      "action": "Senate/ received fiscal note from Fiscal Analyst in Senate Judiciary, Law Enforcement, and Criminal Justice Committee",
      "chamber": "S",
      "chamber_id": 94,
      "importance": 0
    },
    {
      "date": "2025-02-13",
      "action": "Senate Comm - Not Considered in Senate Judiciary, Law Enforcement, and Criminal Justice Committee",
      "chamber": "S",
      "chamber_id": 94,
      "importance": 0
    },
    {
      "date": "2025-02-18",
      "action": "Senate Comm - Substitute Recommendation in Senate Judiciary, Law Enforcement, and Criminal Justice Committee",
      "chamber": "S",
      "chamber_id": 94,
      "importance": 0
    },
    {
      "date": "2025-02-18",
      "action": "Senate Comm - Amendment Recommendation in Senate Judiciary, Law Enforcement, and Criminal Justice Committee",
      "chamber": "S",
      "chamber_id": 94,
      "importance": 0
    },
    {
      "date": "2025-02-18",
      "action": "Senate Comm - Favorable Recommendation in Senate Judiciary, Law Enforcement, and Criminal Justice Committee",
      "chamber": "S",
      "chamber_id": 94,
      "importance": 0
    },
    {
      "date": "2025-02-18",
      "action": "Senate/ comm rpt/ substituted/ amended in Senate Judiciary, Law Enforcement, and Criminal Justice Committee",
      "chamber": "S",
      "chamber_id": 94,
      "importance": 1
    },
    {
      "date": "2025-02-18",
      "action": "Senate/ placed on 2nd Reading Calendar in Senate 2nd Reading Calendar",
      "chamber": "S",
      "chamber_id": 94,
      "importance": 0
    },
    {
      "date": "2025-02-21",
      "action": "Senate/ 2nd reading in Senate 2nd Reading Calendar",
      "chamber": "S",
      "chamber_id": 94,
      "importance": 0
    },
    {
      "date": "2025-02-21",
      "action": "Senate/ substituted in Senate 2nd Reading Calendar",
      "chamber": "S",
      "chamber_id": 94,
      "importance": 0
    },
    {
      "date": "2025-02-21",
      "action": "Senate/ passed 2nd reading in Senate 3rd Reading Calendar",
      "chamber": "S",
      "chamber_id": 94,
      "importance": 0
    },
    {
      "date": "2025-02-24",
      "action": "Senate/ 3rd reading in Senate 3rd Reading Calendar",
      "chamber": "S",
      "chamber_id": 94,
      "importance": 0
    },
    {
      "date": "2025-02-24",
      "action": "Senate/ circled in Senate 3rd Reading Calendar",
      "chamber": "S",
      "chamber_id": 94,
      "importance": 0
    },
    {
      "date": "2025-02-27",
      "action": "Senate/ uncircled in Senate 3rd Reading Calendar",
      "chamber": "S",
      "chamber_id": 94,
      "importance": 0
    },
    {
      "date": "2025-02-27",
      "action": "Senate/ substituted in Senate 3rd Reading Calendar",
      "chamber": "S",
      "chamber_id": 94,
      "importance": 0
    },
    {
      "date": "2025-02-27",
      "action": "Senate/ circled in Senate 3rd Reading Calendar",
      "chamber": "S",
      "chamber_id": 94,
      "importance": 0
    },
    {
      "date": "2025-02-27",
      "action": "Senate/ uncircled in Senate 3rd Reading Calendar",
      "chamber": "S",
      "chamber_id": 94,
      "importance": 0
    },
    {
      "date": "2025-02-27",
      "action": "Senate/ passed 3rd reading in Clerk of the House",
      "chamber": "H",
      "chamber_id": 93,
      "importance": 0
    },
    {
      "date": "2025-02-27",
      "action": "Senate/ to House in Clerk of the House",
      "chamber": "H",
      "chamber_id": 93,
      "importance": 0
    },
    {
      "date": "2025-02-27",
      "action": "House/ received from Senate in Clerk of the House",
      "chamber": "H",
      "chamber_id": 93,
      "importance": 1
    },
    {
      "date": "2025-02-28",
      "action": "House/ 1st reading (Introduced) in House Rules Committee",
      "chamber": "H",
      "chamber_id": 93,
      "importance": 0
    },
    {
      "date": "2025-03-03",
      "action": "House/ to standing committee in House Law Enforcement and Criminal Justice Committee",
      "chamber": "H",
      "chamber_id": 93,
      "importance": 1
    },
    {
      "date": "2025-03-04",
      "action": "House Comm - Substitute Recommendation in House Law Enforcement and Criminal Justice Committee",
      "chamber": "H",
      "chamber_id": 93,
      "importance": 0
    },
    {
      "date": "2025-03-04",
      "action": "House Comm - Favorable Recommendation in House Law Enforcement and Criminal Justice Committee",
      "chamber": "H",
      "chamber_id": 93,
      "importance": 0
    },
    {
      "date": "2025-03-04",
      "action": "House/ comm rpt/ substituted in House Law Enforcement and Criminal Justice Committee",
      "chamber": "H",
      "chamber_id": 93,
      "importance": 1
    },
    {
      "date": "2025-03-04",
      "action": "House/ return to Rules due to fiscal impact in House Rules Committee",
      "chamber": "H",
      "chamber_id": 93,
      "importance": 0
    }
  ],
  "sponsors": [
    {
      "people_id": 13816,
      "person_hash": "pbt6z55h",
      "party_id": "2",
      "state_id": 44,
      "party": "R",
      "role_id": 2,
      "role": "Sen",
      "name": "Todd Weiler",
      "first_name": "Todd",
      "middle_name": "D.",
      "last_name": "Weiler",
      "suffix": "",
      "nickname": "",
      "district": "SD-008",
      "ftm_eid": 6648183,
      "votesmart_id": 50569,
      "opensecrets_id": "",
      "knowwho_pid": 390467,
      "ballotpedia": "Todd_Weiler",
      "bioguide_id": "",
      "sponsor_type_id": 1,
      "sponsor_order": 1,
      "committee_sponsor": 0,
      "committee_id": 0,
      "state_federal": 0
    },
    {
      "people_id": 8151,
      "person_hash": "e4w8e50x",
      "party_id": "2",
      "state_id": 44,
      "party": "R",
      "role_id": 1,
      "role": "Rep",
      "name": "Ryan Wilcox",
      "first_name": "Ryan",
      "middle_name": "D.",
      "last_name": "Wilcox",
      "suffix": "",
      "nickname": "",
      "district": "HD-007",
      "ftm_eid": 6675652,
      "votesmart_id": 103559,
      "opensecrets_id": "",
      "knowwho_pid": 268620,
      "ballotpedia": "Ryan_Wilcox",
      "bioguide_id": "",
      "sponsor_type_id": 3,
      "sponsor_order": 2,
      "committee_sponsor": 0,
      "committee_id": 0,
      "state_federal": 0
    }
  ],
  "sasts": [],
  "subjects": [
    {
      "subject_id": 11866,
      "subject_name": "Law Enforcement and Criminal Justice"
    },
    {
      "subject_id": 12001,
      "subject_name": "Electronic Information"
    },
    {
      "subject_id": 12074,
      "subject_name": "Attorneys"
    },
    {
      "subject_id": 332709,
      "subject_name": "Peace Officers"
    }
  ],
  "texts": [
    {
      "doc_id": 3111334,
      "date": "2025-02-10",
      "type": "Introduced",
      "type_id": 1,
      "mime": "application/pdf",
      "mime_id": 2,
      "url": "https://legiscan.com/UT/text/SB0252/id/3111334",
      "state_link": "https://le.utah.gov/Session/2025/bills/introduced/SB0252.pdf",
      "text_size": 52781,
      "text_hash": "307dc2cabab5d6f9fe5437ca25ecc276",
      "alt_bill_text": 0,
      "alt_mime": "",
      "alt_mime_id": 0,
      "alt_state_link": "",
      "alt_text_size": 0,
      "alt_text_hash": ""
    },
    {
      "doc_id": 3117437,
      "date": "2025-02-12",
      "type": "Substitute",
      "type_id": 14,
      "mime": "application/pdf",
      "mime_id": 2,
      "url": "https://legiscan.com/UT/text/SB0252/id/3117437",
      "state_link": "https://le.utah.gov/Session/2025/bills/introduced/SB0252S01.pdf",
      "text_size": 53776,
      "text_hash": "984510ab195b1d20dcc9e7c3d8adb0d4",
      "alt_bill_text": 0,
      "alt_mime": "",
      "alt_mime_id": 0,
      "alt_state_link": "",
      "alt_text_size": 0,
      "alt_text_hash": ""
    },
    {
      "doc_id": 3127864,
      "date": "2025-02-18",
      "type": "Amended",
      "type_id": 3,
      "mime": "application/pdf",
      "mime_id": 2,
      "url": "https://legiscan.com/UT/text/SB0252/id/3127864",
      "state_link": "https://le.utah.gov/Session/2025/bills/amended/AV_SB0252S01_2025-02-18_11-35-04.pdf",
      "text_size": 65237,
      "text_hash": "59b4fe188c7de512988526c8c62925cf",
      "alt_bill_text": 0,
      "alt_mime": "",
      "alt_mime_id": 0,
      "alt_state_link": "",
      "alt_text_size": 0,
      "alt_text_hash": ""
    },
    {
      "doc_id": 3134167,
      "date": "2025-02-20",
      "type": "Substitute",
      "type_id": 14,
      "mime": "application/pdf",
      "mime_id": 2,
      "url": "https://legiscan.com/UT/text/SB0252/id/3134167",
      "state_link": "https://le.utah.gov/Session/2025/bills/introduced/SB0252S02.pdf",
      "text_size": 59935,
      "text_hash": "7e38cfffdcc33759fe2e6cdd5f8dc11a",
      "alt_bill_text": 0,
      "alt_mime": "",
      "alt_mime_id": 0,
      "alt_state_link": "",
      "alt_text_size": 0,
      "alt_text_hash": ""
    },
    {
      "doc_id": 3146499,
      "date": "2025-02-27",
      "type": "Substitute",
      "type_id": 14,
      "mime": "application/pdf",
      "mime_id": 2,
      "url": "https://legiscan.com/UT/text/SB0252/id/3146499",
      "state_link": "https://le.utah.gov/Session/2025/bills/introduced/SB0252S03.pdf",
      "text_size": 61013,
      "text_hash": "d985091bdfad9031b598abe956a11312",
      "alt_bill_text": 0,
      "alt_mime": "",
      "alt_mime_id": 0,
      "alt_state_link": "",
      "alt_text_size": 0,
      "alt_text_hash": ""
    },
    {
      "doc_id": 3153472,
      "date": "2025-03-04",
      "type": "Substitute",
      "type_id": 14,
      "mime": "application/pdf",
      "mime_id": 2,
      "url": "https://legiscan.com/UT/text/SB0252/id/3153472",
      "state_link": "https://le.utah.gov/Session/2025/bills/introduced/SB0252S04.pdf",
      "text_size": 59915,
      "text_hash": "67bd258d25a1b0be0a22b085653c179e",
      "alt_bill_text": 0,
      "alt_mime": "",
      "alt_mime_id": 0,
      "alt_state_link": "",
      "alt_text_size": 0,
      "alt_text_hash": ""
    }
  ],
  "votes": [],
  "amendments": [
    {
      "amendment_id": 229503,
      "adopted": 1,
      "chamber": "S",
      "chamber_id": 94,
      "date": "2025-02-18",
      "title": "Senate Amendment 1",
      "description": "Senate Amendment 1",
      "mime": "application/pdf",
      "mime_id": 2,
      "url": "https://legiscan.com/UT/amendment/SB0252/id/229503",
      "state_link": "https://le.utah.gov/Session/2025/bills/amended/SB0252S01.Samd.1.pdf",
      "amendment_size": 6380,
      "amendment_hash": "ce7388ac3670b1c8042d99e3fb170cda",
      "alt_amendment": 0,
      "alt_mime": "",
      "alt_mime_id": 0,
      "alt_state_link": "",
      "alt_amendment_size": 0,
      "alt_amendment_hash": ""
    }
  ],
  "supplements": [
    {
      "supplement_id": 513965,
      "date": "2025-02-12",
      "type": "Fiscal Note",
      "type_id": 1,
      "title": "Fiscal Note",
      "description": "Fiscal Note SB0252",
      "mime": "application/pdf",
      "mime_id": 2,
      "url": "https://legiscan.com/UT/supplement/SB0252/id/513965",
      "state_link": "https://pf.utleg.gov/public-web/sessions/2025GS/fiscal-notes/SB0252.fn.pdf",
      "supplement_size": 1609371,
      "supplement_hash": "77606e22040790d85ab3ba06f8ee46b8",
      "alt_supplement": 0,
      "alt_mime": "",
      "alt_mime_id": 0,
      "alt_state_link": "",
      "alt_supplement_size": 0,
      "alt_supplement_hash": ""
    },
    {
      "supplement_id": 514844,
      "date": "2025-02-12",
      "type": "Misc",
      "type_id": 7,
      "title": "Misc",
      "description": "Comparison to Sub #0",
      "mime": "application/pdf",
      "mime_id": 2,
      "url": "https://legiscan.com/UT/supplement/SB0252/id/514844",
      "state_link": "https://le.utah.gov/Session/2025/bills/introduced/CP%20SB0252%20To%20SB0252S01.pdf",
      "supplement_size": 52308,
      "supplement_hash": "616ea2ad814360f86e9c83dbfee99913",
      "alt_supplement": 0,
      "alt_mime": "",
      "alt_mime_id": 0,
      "alt_state_link": "",
      "alt_supplement_size": 0,
      "alt_supplement_hash": ""
    },
    {
      "supplement_id": 516642,
      "date": "2025-02-14",
      "type": "Fiscal Note",
      "type_id": 1,
      "title": "Fiscal Note",
      "description": "Fiscal Note SB0252S01",
      "mime": "application/pdf",
      "mime_id": 2,
      "url": "https://legiscan.com/UT/supplement/SB0252/id/516642",
      "state_link": "https://pf.utleg.gov/public-web/sessions/2025GS/fiscal-notes/SB0252S01.fn.pdf",
      "supplement_size": 1609404,
      "supplement_hash": "29934aae415587cbe729cd3445e0523c",
      "alt_supplement": 0,
      "alt_mime": "",
      "alt_mime_id": 0,
      "alt_state_link": "",
      "alt_supplement_size": 0,
      "alt_supplement_hash": ""
    },
    {
      "supplement_id": 521479,
      "date": "2025-02-18",
      "type": "Misc",
      "type_id": 7,
      "title": "Misc",
      "description": "Senate Committee Report SB0252",
      "mime": "application/pdf",
      "mime_id": 2,
      "url": "https://legiscan.com/UT/supplement/SB0252/id/521479",
      "state_link": "https://le.utah.gov/Session/2025/comreport/SB252S10.pdf",
      "supplement_size": 160722,
      "supplement_hash": "18c97f858aa94e48ec435edd5b50d717",
      "alt_supplement": 0,
      "alt_mime": "",
      "alt_mime_id": 0,
      "alt_state_link": "",
      "alt_supplement_size": 0,
      "alt_supplement_hash": ""
    },
    {
      "supplement_id": 525095,
      "date": "2025-02-20",
      "type": "Misc",
      "type_id": 7,
      "title": "Misc",
      "description": "Comparison to Sub #0",
      "mime": "application/pdf",
      "mime_id": 2,
      "url": "https://legiscan.com/UT/supplement/SB0252/id/525095",
      "state_link": "https://le.utah.gov/Session/2025/bills/introduced/CP%20SB0252%20To%20SB0252S02.pdf",
      "supplement_size": 72408,
      "supplement_hash": "8846cd7802b30826f8f058a4370cdb35",
      "alt_supplement": 0,
      "alt_mime": "",
      "alt_mime_id": 0,
      "alt_state_link": "",
      "alt_supplement_size": 0,
      "alt_supplement_hash": ""
    },
    {
      "supplement_id": 525096,
      "date": "2025-02-20",
      "type": "Misc",
      "type_id": 7,
      "title": "Misc",
      "description": "Comparison to Sub #1",
      "mime": "application/pdf",
      "mime_id": 2,
      "url": "https://legiscan.com/UT/supplement/SB0252/id/525096",
      "state_link": "https://le.utah.gov/Session/2025/bills/introduced/CP%20SB0252S01%20To%20SB0252S02.pdf",
      "supplement_size": 84358,
      "supplement_hash": "677648188b2832fa6da1f65d2a91b6d9",
      "alt_supplement": 0,
      "alt_mime": "",
      "alt_mime_id": 0,
      "alt_state_link": "",
      "alt_supplement_size": 0,
      "alt_supplement_hash": ""
    },
    {
      "supplement_id": 527441,
      "date": "2025-02-24",
      "type": "Fiscal Note",
      "type_id": 1,
      "title": "Fiscal Note",
      "description": "Fiscal Note SB0252S02",
      "mime": "application/pdf",
      "mime_id": 2,
      "url": "https://legiscan.com/UT/supplement/SB0252/id/527441",
      "state_link": "https://pf.utleg.gov/public-web/sessions/2025GS/fiscal-notes/SB0252S02.fn.pdf",
      "supplement_size": 1609404,
      "supplement_hash": "1bd636ed410499f075e6806d4b66a4b9",
      "alt_supplement": 0,
      "alt_mime": "",
      "alt_mime_id": 0,
      "alt_state_link": "",
      "alt_supplement_size": 0,
      "alt_supplement_hash": ""
    },
    {
      "supplement_id": 531665,
      "date": "2025-02-27",
      "type": "Misc",
      "type_id": 7,
      "title": "Misc",
      "description": "Comparison to Sub #0",
      "mime": "application/pdf",
      "mime_id": 2,
      "url": "https://legiscan.com/UT/supplement/SB0252/id/531665",
      "state_link": "https://le.utah.gov/Session/2025/bills/introduced/CP%20SB0252%20To%20SB0252S03.pdf",
      "supplement_size": 60927,
      "supplement_hash": "77243d324d7a7221c0c757da618fb894",
      "alt_supplement": 0,
      "alt_mime": "",
      "alt_mime_id": 0,
      "alt_state_link": "",
      "alt_supplement_size": 0,
      "alt_supplement_hash": ""
    },
    {
      "supplement_id": 531666,
      "date": "2025-02-27",
      "type": "Misc",
      "type_id": 7,
      "title": "Misc",
      "description": "Comparison to Sub #1",
      "mime": "application/pdf",
      "mime_id": 2,
      "url": "https://legiscan.com/UT/supplement/SB0252/id/531666",
      "state_link": "https://le.utah.gov/Session/2025/bills/introduced/CP%20SB0252S01%20To%20SB0252S03.pdf",
      "supplement_size": 80677,
      "supplement_hash": "d4525e4bac30ca2e2cd431fcbbe23800",
      "alt_supplement": 0,
      "alt_mime": "",
      "alt_mime_id": 0,
      "alt_state_link": "",
      "alt_supplement_size": 0,
      "alt_supplement_hash": ""
    },
    {
      "supplement_id": 531667,
      "date": "2025-02-27",
      "type": "Misc",
      "type_id": 7,
      "title": "Misc",
      "description": "Comparison to Sub #2",
      "mime": "application/pdf",
      "mime_id": 2,
      "url": "https://legiscan.com/UT/supplement/SB0252/id/531667",
      "state_link": "https://le.utah.gov/Session/2025/bills/introduced/CP%20SB0252S02%20To%20SB0252S03.pdf",
      "supplement_size": 60865,
      "supplement_hash": "87b97133b6e94b8be6db303da366db57",
      "alt_supplement": 0,
      "alt_mime": "",
      "alt_mime_id": 0,
      "alt_state_link": "",
      "alt_supplement_size": 0,
      "alt_supplement_hash": ""
    },
    {
      "supplement_id": 534702,
      "date": "2025-03-03",
      "type": "Fiscal Note",
      "type_id": 1,
      "title": "Fiscal Note",
      "description": "Fiscal Note SB0252S03",
      "mime": "application/pdf",
      "mime_id": 2,
      "url": "https://legiscan.com/UT/supplement/SB0252/id/534702",
      "state_link": "https://pf.utleg.gov/public-web/sessions/2025GS/fiscal-notes/SB0252S03.fn.pdf",
      "supplement_size": 1609379,
      "supplement_hash": "2951330c0018fcee131bfa7a1570495c",
      "alt_supplement": 0,
      "alt_mime": "",
      "alt_mime_id": 0,
      "alt_state_link": "",
      "alt_supplement_size": 0,
      "alt_supplement_hash": ""
    },
    {
      "supplement_id": 537007,
      "date": "2025-03-04",
      "type": "Misc",
      "type_id": 7,
      "title": "Misc",
      "description": "Comparison to Sub #0",
      "mime": "application/pdf",
      "mime_id": 2,
      "url": "https://legiscan.com/UT/supplement/SB0252/id/537007",
      "state_link": "https://le.utah.gov/Session/2025/bills/introduced/CP%20SB0252%20To%20SB0252S04.pdf",
      "supplement_size": 78096,
      "supplement_hash": "ad95cde836e88c8fa854e90575a0c47a",
      "alt_supplement": 0,
      "alt_mime": "",
      "alt_mime_id": 0,
      "alt_state_link": "",
      "alt_supplement_size": 0,
      "alt_supplement_hash": ""
    },
    {
      "supplement_id": 537008,
      "date": "2025-03-04",
      "type": "Misc",
      "type_id": 7,
      "title": "Misc",
      "description": "Comparison to Sub #1",
      "mime": "application/pdf",
      "mime_id": 2,
      "url": "https://legiscan.com/UT/supplement/SB0252/id/537008",
      "state_link": "https://le.utah.gov/Session/2025/bills/introduced/CP%20SB0252S01%20To%20SB0252S04.pdf",
      "supplement_size": 93990,
      "supplement_hash": "0f7f1eed0c24d4394211ea3a15489882",
      "alt_supplement": 0,
      "alt_mime": "",
      "alt_mime_id": 0,
      "alt_state_link": "",
      "alt_supplement_size": 0,
      "alt_supplement_hash": ""
    },
    {
      "supplement_id": 537009,
      "date": "2025-03-04",
      "type": "Misc",
      "type_id": 7,
      "title": "Misc",
      "description": "Comparison to Sub #2",
      "mime": "application/pdf",
      "mime_id": 2,
      "url": "https://legiscan.com/UT/supplement/SB0252/id/537009",
      "state_link": "https://le.utah.gov/Session/2025/bills/introduced/CP%20SB0252S02%20To%20SB0252S04.pdf",
      "supplement_size": 69467,
      "supplement_hash": "fc7336974fb7639719a2e774ef6a9f22",
      "alt_supplement": 0,
      "alt_mime": "",
      "alt_mime_id": 0,
      "alt_state_link": "",
      "alt_supplement_size": 0,
      "alt_supplement_hash": ""
    },
    {
      "supplement_id": 537010,
      "date": "2025-03-04",
      "type": "Misc",
      "type_id": 7,
      "title": "Misc",
      "description": "Comparison to Sub #3",
      "mime": "application/pdf",
      "mime_id": 2,
      "url": "https://legiscan.com/UT/supplement/SB0252/id/537010",
      "state_link": "https://le.utah.gov/Session/2025/bills/introduced/CP%20SB0252S03%20To%20SB0252S04.pdf",
      "supplement_size": 70299,
      "supplement_hash": "01b265d4e8c7d158d7445b97bdbeefa2",
      "alt_supplement": 0,
      "alt_mime": "",
      "alt_mime_id": 0,
      "alt_state_link": "",
      "alt_supplement_size": 0,
      "alt_supplement_hash": ""
    },
    {
      "supplement_id": 537011,
      "date": "2025-03-04",
      "type": "Misc",
      "type_id": 7,
      "title": "Misc",
      "description": "House Committee Report SB0252",
      "mime": "application/pdf",
      "mime_id": 2,
      "url": "https://legiscan.com/UT/supplement/SB0252/id/537011",
      "state_link": "https://le.utah.gov/Session/2025/comreport/SB252H10.pdf",
      "supplement_size": 147364,
      "supplement_hash": "9bcd26bc298420ad7a15f67cb318e487",
      "alt_supplement": 0,
      "alt_mime": "",
      "alt_mime_id": 0,
      "alt_state_link": "",
      "alt_supplement_size": 0,
      "alt_supplement_hash": ""
    },
    {
      "supplement_id": 537264,
      "date": "2025-03-05",
      "type": "Fiscal Note",
      "type_id": 1,
      "title": "Fiscal Note",
      "description": "Fiscal Note SB0252S04",
      "mime": "application/pdf",
      "mime_id": 2,
      "url": "https://legiscan.com/UT/supplement/SB0252/id/537264",
      "state_link": "https://pf.utleg.gov/public-web/sessions/2025GS/fiscal-notes/SB0252S04.fn.pdf",
      "supplement_size": 1609493,
      "supplement_hash": "ec1981b198d2a797ed6c612dc6e3ca8f",
      "alt_supplement": 0,
      "alt_mime": "",
      "alt_mime_id": 0,
      "alt_state_link": "",
      "alt_supplement_size": 0,
      "alt_supplement_hash": ""
    }
  ],
  "calendar": [
    {
      "type_id": 1,
      "event_hash": "56ce5ea6",
      "type": "Hearing",
      "date": "2025-02-13",
      "time": "14:00",
      "location": "Room 30 House Building",
      "description": "Senate Judiciary, Law Enforcement, and Criminal Justice Hearing"
    },
    {
      "type_id": 1,
      "event_hash": "7506e9d2",
      "type": "Hearing",
      "date": "2025-02-18",
      "time": "08:00",
      "location": "Room 30 House Building",
      "description": "Senate Judiciary, Law Enforcement, and Criminal Justice Hearing"
    },
    {
      "type_id": 1,
      "event_hash": "224be394",
      "type": "Hearing",
      "date": "2025-03-04",
      "time": "16:00",
      "location": "",
      "description": "House Law Enforcement and Criminal Justice Hearing"
    }
  ],
  "general_provisions": "This bill concerns digital information contained on a computer or portable communication device seized by law enforcement.",
  "hilighted_provisions": "This bill:<hr><ltbullet>defines terms and modifies definitions;<hr><ltbullet>provides specific procedures and requirements regarding the copying and return of digital data on certain seized computers or portable communication devices;<hr><ltbullet>prohibits a law enforcement agency or prosecuting agency from conditioning the return of digital data from a seized computer or portable communication device on the owner consenting to a search of the computer or portable communication device or providing the owner's password or otherwise unlocking the computer or portable communication device; <hr><ltbullet>requires a prosecuting attorney to notify the agency with custody of a seized computer or portable communication device within a specific time period when the prosecuting attorney determines that the computer or portable communication device no longer needs to be retained as evidence; and<hr><ltbullet>makes technical and conforming changes.",
  "monies": "None",
  "attorney": "Jackie Rogers",
  "fiscal_analyst": "Joseph Ryan Fitzgerald",
  "gov_tracking_id": "PVTXWVIQUE",
  "comrecommend": [],
  "agendas": [
    {
      "mtgID": "19949",
      "committeeID": "HSTLAW",
      "mtgDate": "2025-03-04 16:00:00.0",
      "agendaItem": "1",
      "mtgPlace": "30 House Building",
      "committeeName": "House Law Enforcement and Criminal Justice Committee",
      "upcomming": false,
      "minutesURL": "/",
      "agendaURL": "/~2025/agenda/HLAW0304.ag.htm",
      "billSession": "2025GS",
      "markerID": "277605"
    },
    {
      "mtgID": "19779",
      "committeeID": "SSTJLC",
      "mtgDate": "2025-02-13 14:00:00.0",
      "agendaItem": "5",
      "mtgPlace": "210 Senate Building",
      "committeeName": "Senate Judiciary, Law Enforcement, and Criminal Justice Committee",
      "upcomming": false,
      "minutesURL": "/interim/2025/html/00001609.htm",
      "agendaURL": "/~2025/agenda/SJLC0213.ag.htm",
      "billSession": "2025GS",
      "markerID": ""
    },
    {
      "mtgID": "19780",
      "committeeID": "SSTJLC",
      "mtgDate": "2025-02-18 08:00:00.0",
      "agendaItem": "6",
      "mtgPlace": "210 Senate Building",
      "committeeName": "Senate Judiciary, Law Enforcement, and Criminal Justice Committee",
      "upcomming": false,
      "minutesURL": "/interim/2025/html/00001659.htm",
      "agendaURL": "/~2025/agenda/SJLC0218.ag.htm",
      "billSession": "2025GS",
      "markerID": "272400"
    }
  ],
  "last_action": "House/ return to Rules due to fiscal impact",
  "last_action_owner": "House Rules Committee",
  "last_action_time": "3/4/2025",
  "action_history": [
    {
      "description": "Bill Numbered but not Distributed",
      "owner": "Legislative Research and General Counsel",
      "actionDate": "2/10/2025 3:43 PM",
      "actionClass": "L",
      "voteID": "",
      "voiceVote": "",
      "voteHouse": "",
      "voteStr": "",
      "actionCode": "LNUMBER",
      "parm1": "",
      "parm2": ""
    },
    {
      "description": "Numbered Bill Publicly Distributed",
      "owner": "Legislative Research and General Counsel",
      "actionDate": "2/10/2025 3:43 PM",
      "actionClass": "L",
      "voteID": "",
      "voiceVote": "",
      "voteHouse": "",
      "voteStr": "",
      "actionCode": "LLFA",
      "parm1": "",
      "parm2": ""
    },
    {
      "description": "Senate/ received bill from Legislative Research",
      "owner": "Waiting for Introduction in the Senate",
      "actionDate": "2/11/2025 7:43 AM",
      "actionClass": "S",
      "voteID": "",
      "voiceVote": "",
      "voteHouse": "",
      "voteStr": "",
      "actionCode": "SRECLRGC",
      "parm1": "",
      "parm2": ""
    },
    {
      "description": "Senate/ 1st reading (Introduced)",
      "owner": "Senate Rules Committee",
      "actionDate": "2/11/2025 11:27 AM",
      "actionClass": "S",
      "voteID": "",
      "voiceVote": "",
      "voteHouse": "",
      "voteStr": "",
      "actionCode": "SREAD1",
      "parm1": "",
      "parm2": ""
    },
    {
      "description": "Senate/ to standing committee",
      "owner": "Senate Judiciary, Law Enforcement, and Criminal Justice Committee",
      "actionDate": "2/11/2025 2:21 PM",
      "actionClass": "S",
      "voteID": "",
      "voiceVote": "",
      "voteHouse": "",
      "voteStr": "",
      "actionCode": "STOSTAND",
      "parm1": "",
      "parm2": ""
    },
    {
      "description": "Senate/ received fiscal note from Fiscal Analyst",
      "owner": "Senate Judiciary, Law Enforcement, and Criminal Justice Committee",
      "actionDate": "2/12/2025 10:53 AM",
      "actionClass": "S",
      "voteID": "",
      "voiceVote": "",
      "voteHouse": "",
      "voteStr": "",
      "actionCode": "SRECLFA",
      "parm1": "",
      "parm2": ""
    },
    {
      "description": "Senate Comm - Not Considered",
      "owner": "Senate Judiciary, Law Enforcement, and Criminal Justice Committee",
      "actionDate": "2/13/2025 2:00 PM",
      "actionClass": "A",
      "voteID": "",
      "voiceVote": "",
      "voteHouse": "",
      "voteStr": "",
      "actionCode": "SCANOCNSDR",
      "parm1": "",
      "parm2": ""
    },
    {
      "description": "Senate Comm - Substitute Recommendation",
      "owner": "Senate Judiciary, Law Enforcement, and Criminal Justice Committee",
      "actionDate": "2/18/2025 9:28 AM",
      "actionClass": "A",
      "voteID": "35796",
      "voiceVote": "",
      "voteHouse": "",
      "voteStr": "7-0-2",
      "actionCode": "SCASUB",
      "parm1": "1",
      "parm2": "0"
    },
    {
      "description": "Senate Comm - Amendment Recommendation",
      "owner": "Senate Judiciary, Law Enforcement, and Criminal Justice Committee",
      "actionDate": "2/18/2025 9:29 AM",
      "actionClass": "A",
      "voteID": "35797",
      "voiceVote": "",
      "voteHouse": "",
      "voteStr": "7-0-2",
      "actionCode": "SCAAMD",
      "parm1": "1",
      "parm2": ""
    },
    {
      "description": "Senate Comm - Favorable Recommendation",
      "owner": "Senate Judiciary, Law Enforcement, and Criminal Justice Committee",
      "actionDate": "2/18/2025 9:47 AM",
      "actionClass": "A",
      "voteID": "35808",
      "voiceVote": "",
      "voteHouse": "",
      "voteStr": "7-0-2",
      "actionCode": "SCAFAV",
      "parm1": "",
      "parm2": ""
    },
    {
      "description": "Senate/ comm rpt/ substituted/ amended",
      "owner": "Senate Judiciary, Law Enforcement, and Criminal Justice Committee",
      "actionDate": "2/18/2025 2:21 PM",
      "actionClass": "S",
      "voteID": "",
      "voiceVote": "",
      "voteHouse": "",
      "voteStr": "",
      "actionCode": "SCRSUBAMD",
      "parm1": "",
      "parm2": ""
    },
    {
      "description": "Senate/ placed on 2nd Reading Calendar",
      "owner": "Senate 2nd Reading Calendar",
      "actionDate": "2/18/2025 2:21 PM",
      "actionClass": "S",
      "voteID": "",
      "voiceVote": "",
      "voteHouse": "",
      "voteStr": "",
      "actionCode": "SON2ND",
      "parm1": "",
      "parm2": ""
    },
    {
      "description": "Senate/ 2nd reading",
      "owner": "Senate 2nd Reading Calendar",
      "actionDate": "2/21/2025 3:35 PM",
      "actionClass": "S",
      "voteID": "",
      "voiceVote": "",
      "voteHouse": "",
      "voteStr": "",
      "actionCode": "SREAD2",
      "parm1": "",
      "parm2": ""
    },
    {
      "description": "Senate/ substituted",
      "owner": "Senate 2nd Reading Calendar",
      "actionDate": "2/21/2025 3:39 PM",
      "actionClass": "S",
      "voteID": "931",
      "voiceVote": "1",
      "voteHouse": "S",
      "voteStr": "0-0-29",
      "actionCode": "SSUB",
      "parm1": "2",
      "parm2": "1"
    },
    {
      "description": "Senate/ passed 2nd reading",
      "owner": "Senate 3rd Reading Calendar",
      "actionDate": "2/21/2025 3:40 PM",
      "actionClass": "S",
      "voteID": "932",
      "voiceVote": "0",
      "voteHouse": "S",
      "voteStr": "24-0-5",
      "actionCode": "SPASS2",
      "parm1": "",
      "parm2": ""
    },
    {
      "description": "Senate/ 3rd reading",
      "owner": "Senate 3rd Reading Calendar",
      "actionDate": "2/24/2025 2:24 PM",
      "actionClass": "S",
      "voteID": "",
      "voiceVote": "",
      "voteHouse": "",
      "voteStr": "",
      "actionCode": "SREAD3",
      "parm1": "",
      "parm2": ""
    },
    {
      "description": "Senate/ circled",
      "owner": "Senate 3rd Reading Calendar",
      "actionDate": "2/24/2025 2:24 PM",
      "actionClass": "S",
      "voteID": "1006",
      "voiceVote": "1",
      "voteHouse": "S",
      "voteStr": "0-0-29",
      "actionCode": "SCIRCLED",
      "parm1": "",
      "parm2": ""
    },
    {
      "description": "Senate/ uncircled",
      "owner": "Senate 3rd Reading Calendar",
      "actionDate": "2/27/2025 2:54 PM",
      "actionClass": "S",
      "voteID": "1302",
      "voiceVote": "1",
      "voteHouse": "S",
      "voteStr": "0-0-29",
      "actionCode": "SUNCIRCLED",
      "parm1": "",
      "parm2": ""
    },
    {
      "description": "Senate/ substituted",
      "owner": "Senate 3rd Reading Calendar",
      "actionDate": "2/27/2025 2:56 PM",
      "actionClass": "S",
      "voteID": "1303",
      "voiceVote": "1",
      "voteHouse": "S",
      "voteStr": "0-0-29",
      "actionCode": "SSUB",
      "parm1": "3",
      "parm2": "2"
    },
    {
      "description": "Senate/ circled",
      "owner": "Senate 3rd Reading Calendar",
      "actionDate": "2/27/2025 2:56 PM",
      "actionClass": "S",
      "voteID": "1304",
      "voiceVote": "1",
      "voteHouse": "S",
      "voteStr": "0-0-29",
      "actionCode": "SCIRCLED",
      "parm1": "",
      "parm2": ""
    },
    {
      "description": "Senate/ uncircled",
      "owner": "Senate 3rd Reading Calendar",
      "actionDate": "2/27/2025 7:38 PM",
      "actionClass": "S",
      "voteID": "1387",
      "voiceVote": "1",
      "voteHouse": "S",
      "voteStr": "0-0-29",
      "actionCode": "SUNCIRCLED",
      "parm1": "",
      "parm2": ""
    },
    {
      "description": "Senate/ passed 3rd reading",
      "owner": "Clerk of the House",
      "actionDate": "2/27/2025 7:49 PM",
      "actionClass": "S",
      "voteID": "1388",
      "voiceVote": "0",
      "voteHouse": "S",
      "voteStr": "25-0-4",
      "actionCode": "SPASS3",
      "parm1": "",
      "parm2": ""
    },
    {
      "description": "Senate/ to House",
      "owner": "Clerk of the House",
      "actionDate": "2/27/2025 7:49 PM",
      "actionClass": "S",
      "voteID": "",
      "voiceVote": "",
      "voteHouse": "",
      "voteStr": "",
      "actionCode": "STOHOU",
      "parm1": "",
      "parm2": ""
    },
    {
      "description": "House/ received from Senate",
      "owner": "Clerk of the House",
      "actionDate": "2/27/2025 8:06 PM",
      "actionClass": "H",
      "voteID": "",
      "voiceVote": "",
      "voteHouse": "",
      "voteStr": "",
      "actionCode": "HRECS",
      "parm1": "",
      "parm2": ""
    },
    {
      "description": "House/ 1st reading (Introduced)",
      "owner": "House Rules Committee",
      "actionDate": "2/28/2025 10:09 AM",
      "actionClass": "H",
      "voteID": "",
      "voiceVote": "",
      "voteHouse": "",
      "voteStr": "",
      "actionCode": "HREAD1",
      "parm1": "",
      "parm2": ""
    },
    {
      "description": "House/ to standing committee",
      "owner": "House Law Enforcement and Criminal Justice Committee",
      "actionDate": "3/3/2025 11:24 AM",
      "actionClass": "H",
      "voteID": "",
      "voiceVote": "",
      "voteHouse": "",
      "voteStr": "",
      "actionCode": "HTOSTAND",
      "parm1": "",
      "parm2": ""
    },
    {
      "description": "House Comm - Substitute Recommendation",
      "owner": "House Law Enforcement and Criminal Justice Committee",
      "actionDate": "3/4/2025 5:16 PM",
      "actionClass": "A",
      "voteID": "37292",
      "voiceVote": "",
      "voteHouse": "",
      "voteStr": "8-0-3",
      "actionCode": "HCASUB",
      "parm1": "4",
      "parm2": "3"
    },
    {
      "description": "House Comm - Favorable Recommendation",
      "owner": "House Law Enforcement and Criminal Justice Committee",
      "actionDate": "3/4/2025 5:20 PM",
      "actionClass": "A",
      "voteID": "37297",
      "voiceVote": "",
      "voteHouse": "",
      "voteStr": "8-1-2",
      "actionCode": "HCAFAV",
      "parm1": "",
      "parm2": ""
    },
    {
      "description": "House/ comm rpt/ substituted",
      "owner": "House Law Enforcement and Criminal Justice Committee",
      "actionDate": "3/4/2025 9:21 PM",
      "actionClass": "H",
      "voteID": "",
      "voiceVote": "",
      "voteHouse": "",
      "voteStr": "",
      "actionCode": "HCRSUB",
      "parm1": "",
      "parm2": ""
    },
    {
      "description": "House/ return to Rules due to fiscal impact",
      "owner": "House Rules Committee",
      "actionDate": "3/4/2025 9:21 PM",
      "actionClass": "H",
      "voteID": "",
      "voiceVote": "",
      "voteHouse": "",
      "voteStr": "",
      "actionCode": "HRETRULFIS",
      "parm1": "",
      "parm2": ""
    }
  ]
}